django_py_zipkin/__init__.py
django_py_zipkin/middleware.py
django_py_zipkin/tasks.py
django_py_zipkin/transport.py
django_py_zipkin-1.0.0.dist-info/METADATA
django_py_zipkin-1.0.0.dist-info/RECORD
django_py_zipkin-1.0.0.dist-info/WHEEL
django_py_zipkin-1.0.0.dist-info/top_level.txt
