Metadata-Version: 2.1
Name: django-py-zipkin
Version: 1.0.0
Summary: py3 compatible zipkin for Django
Home-page: https://github.com/praekeltfoundation/django-py-zipkin
Author: Simon de Haan
Author-email: simon@praekelt.org
License: UNKNOWN
Keywords: zipkin
Platform: UNKNOWN
Classifier: Intended Audience :: Developers
Classifier: Natural Language :: English
Classifier: Programming Language :: Python :: 3.6
Provides-Extra: dev
Requires-Dist: Django
Requires-Dist: celery
Requires-Dist: requests
Requires-Dist: py-zipkin (==0.8.3)
Provides-Extra: dev
Requires-Dist: pytest (<4.0,>=3.6); extra == 'dev'
Requires-Dist: pytest-xdist; extra == 'dev'
Requires-Dist: pytest-django (<4.0,>=3.3.3); extra == 'dev'
Requires-Dist: mock; extra == 'dev'
Requires-Dist: responses; extra == 'dev'
Requires-Dist: flake8; extra == 'dev'
